{"environment":"static","source":"local","mode":"compressed","path":"http:\/\/localhost\/framework\/2017\/06June\/theme3461\/media\/foundry\/3.1","extension":".min.js","rootPath":"http:\/\/localhost\/framework\/2017\/06June\/theme3461","basePath":"http:\/\/localhost\/framework\/2017\/06June\/theme3461","indexUrl":"http:\/\/localhost\/framework\/2017\/06June\/theme3461\/index.php","joomla":{"version":"3.6.5","debug":false},"locale":{"lang":"en-GB"},"modified":1490949810,"foundry_version":"3.1.17"}